nhl_stats/__init__.py
nhl_stats/sdk.py
nhl_stats/hooks/__init__.py
nhl_stats/hooks/hook.py
nhl_stats/models/__init__.py
nhl_stats/models/base.py
nhl_stats/models/utils/cast_models.py
nhl_stats/models/utils/json_map.py
nhl_stats/net/__init__.py
nhl_stats/net/environment/__init__.py
nhl_stats/net/environment/environment.py
nhl_stats/net/headers/__init__.py
nhl_stats/net/headers/base_header.py
nhl_stats/net/request_chain/__init__.py
nhl_stats/net/request_chain/request_chain.py
nhl_stats/net/request_chain/handlers/__init__.py
nhl_stats/net/request_chain/handlers/base_handler.py
nhl_stats/net/request_chain/handlers/hook_handler.py
nhl_stats/net/request_chain/handlers/http_handler.py
nhl_stats/net/request_chain/handlers/retry_handler.py
nhl_stats/net/transport/__init__.py
nhl_stats/net/transport/request.py
nhl_stats/net/transport/request_error.py
nhl_stats/net/transport/response.py
nhl_stats/net/transport/serializer.py
nhl_stats/net/transport/utils.py
nhl_stats/services/__init__.py
nhl_stats/services/draft.py
nhl_stats/services/game.py
nhl_stats/services/goalies.py
nhl_stats/services/miscellaneous.py
nhl_stats/services/players.py
nhl_stats/services/season.py
nhl_stats/services/skaters.py
nhl_stats/services/teams.py
nhl_stats/services/utils/base_service.py
nhl_stats/services/utils/default_headers.py
nhl_stats/services/utils/validator.py
nhl_stats_client-1.0.0.dist-info/LICENSE
nhl_stats_client-1.0.0.dist-info/METADATA
nhl_stats_client-1.0.0.dist-info/WHEEL
nhl_stats_client-1.0.0.dist-info/top_level.txt
nhl_stats_client-1.0.0.dist-info/RECORD
