Metadata-Version: 2.1
Name: nhl-stats-client
Version: 1.0.0
Summary: This section provides documentation for the NHL Stats API. Based on the unofficial documentation https://github.com/Zmalski/NHL-API-Reference
License: MIT
Requires-Python: >=3.7
License-File: LICENSE
Requires-Dist: requests >=2.31.0
